pyfnalsnow/Incident.py
pyfnalsnow/RITM.py
pyfnalsnow/Request.py
pyfnalsnow/__init__.py
pyfnalsnow/ticket.py
pyfnalsnow-1.4.5.dist-info/LICENSE
pyfnalsnow-1.4.5.dist-info/METADATA
pyfnalsnow-1.4.5.dist-info/WHEEL
pyfnalsnow-1.4.5.dist-info/top_level.txt
pyfnalsnow-1.4.5.dist-info/RECORD
