Metadata-Version: 2.1
Name: pyfnalsnow
Version: 1.4.5
Summary: SNOW JSON API access
Home-page: https://github.com/tskirvin/pyfnalsnow.git
Author: Tim Skirvin
Author-email: tskirvin@fnal.gov
Maintainer: Tim Skirvin
Maintainer-email: tskirvin@fnal.gov
License: Perl Artistic
Keywords: snow,service-now
Platform: UNKNOWN
Requires-Dist: pysnow (>=0.7.4)
Requires-Dist: PyYAML (>=3.11)
